{
    "overall": {
        "total images": 56208,
        "total annotations": 8067,
        "no of categories": 11,
        "positive samples": 7366,
        "negative samples": 48842,
        "class distribution": {
            "araneae": 551,
            "cantharidae": 3,
            "carabidae": 2615,
            "coccinellidae": 51,
            "dermaptera": 46,
            "diptera-hymenoptera": 3256,
            "isopoda": 62,
            "myriapoda": 327,
            "opiliones": 48,
            "staphylinidae": 962,
            "coleoptera (larvae)": 146
        }
    },
    "per file": {
        "LG-OSR-HF2F20-07-13_fl": {
            "total images": 582,
            "total annotations": 62,
            "no of categories": 11,
            "positive samples": 58,
            "negative samples": 524,
            "class distribution": {
                "araneae": 2,
                "carabidae": 27,
                "diptera-hymenoptera": 19,
                "myriapoda": 1,
                "staphylinidae": 13
            }
        },
        "LG-OSR-LS3E20-06-15_fl": {
            "total images": 459,
            "total annotations": 34,
            "no of categories": 11,
            "positive samples": 34,
            "negative samples": 425,
            "class distribution": {
                "carabidae": 22,
                "diptera-hymenoptera": 3,
                "myriapoda": 1,
                "staphylinidae": 8
            }
        },
        "LG-OSR-LF1D20-06-30_fl": {
            "total images": 528,
            "total annotations": 25,
            "no of categories": 11,
            "positive samples": 25,
            "negative samples": 503,
            "class distribution": {
                "araneae": 1,
                "carabidae": 16,
                "myriapoda": 5,
                "staphylinidae": 3
            }
        },
        "LG-OSR-LF1G20-07-09_fl": {
            "total images": 564,
            "total annotations": 34,
            "no of categories": 11,
            "positive samples": 32,
            "negative samples": 532,
            "class distribution": {
                "carabidae": 27,
                "diptera-hymenoptera": 2,
                "myriapoda": 2,
                "staphylinidae": 3
            }
        },
        "WW-OSR-HF2F20-06-22_fl": {
            "total images": 421,
            "total annotations": 18,
            "no of categories": 11,
            "positive samples": 17,
            "negative samples": 404,
            "class distribution": {
                "araneae": 1,
                "carabidae": 14,
                "isopoda": 1,
                "staphylinidae": 2
            }
        },
        "LG-OSR-LF1G20-07-01_fl": {
            "total images": 502,
            "total annotations": 38,
            "no of categories": 11,
            "positive samples": 37,
            "negative samples": 465,
            "class distribution": {
                "araneae": 2,
                "carabidae": 30,
                "myriapoda": 3,
                "staphylinidae": 3
            }
        },
        "LG-OSR-LS3E20-07-06_fl": {
            "total images": 471,
            "total annotations": 41,
            "no of categories": 11,
            "positive samples": 39,
            "negative samples": 432,
            "class distribution": {
                "araneae": 1,
                "carabidae": 3,
                "myriapoda": 5,
                "staphylinidae": 32
            }
        },
        "GH-OSR-LF1F20-06-08_fl": {
            "total images": 493,
            "total annotations": 48,
            "no of categories": 11,
            "positive samples": 46,
            "negative samples": 447,
            "class distribution": {
                "araneae": 3,
                "carabidae": 13,
                "myriapoda": 6,
                "staphylinidae": 26
            }
        },
        "GH-OSR-NARS2620-06-02": {
            "total images": 900,
            "total annotations": 41,
            "no of categories": 11,
            "positive samples": 39,
            "negative samples": 861,
            "class distribution": {
                "cantharidae": 2,
                "coleoptera (larvae)": 4,
                "diptera-hymenoptera": 35
            }
        },
        "LG-OSR-LF2F20-07-09_fl": {
            "total images": 593,
            "total annotations": 33,
            "no of categories": 11,
            "positive samples": 33,
            "negative samples": 560,
            "class distribution": {
                "carabidae": 21,
                "dermaptera": 1,
                "myriapoda": 9,
                "staphylinidae": 2
            }
        },
        "LG-OSR-LF1D20-07-08_fl": {
            "total images": 672,
            "total annotations": 76,
            "no of categories": 11,
            "positive samples": 73,
            "negative samples": 599,
            "class distribution": {
                "carabidae": 59,
                "diptera-hymenoptera": 8,
                "isopoda": 2,
                "myriapoda": 1,
                "staphylinidae": 6
            }
        },
        "LG-OSR-LF2F20-07-01_fl": {
            "total images": 484,
            "total annotations": 211,
            "no of categories": 11,
            "positive samples": 196,
            "negative samples": 288,
            "class distribution": {
                "araneae": 5,
                "carabidae": 16,
                "diptera-hymenoptera": 171,
                "isopoda": 2,
                "myriapoda": 1,
                "staphylinidae": 16
            }
        },
        "GH-OSR-LF1F20-06-11_fl": {
            "total images": 531,
            "total annotations": 143,
            "no of categories": 11,
            "positive samples": 128,
            "negative samples": 403,
            "class distribution": {
                "araneae": 1,
                "carabidae": 106,
                "diptera-hymenoptera": 1,
                "isopoda": 2,
                "staphylinidae": 33
            }
        },
        "WW-OSR-LF2F20-06-25_fl": {
            "total images": 535,
            "total annotations": 146,
            "no of categories": 11,
            "positive samples": 121,
            "negative samples": 414,
            "class distribution": {
                "araneae": 1,
                "carabidae": 5,
                "diptera-hymenoptera": 129,
                "isopoda": 6,
                "staphylinidae": 5
            }
        },
        "WW-OSR-LF1D20-06-24_fl": {
            "total images": 460,
            "total annotations": 32,
            "no of categories": 11,
            "positive samples": 30,
            "negative samples": 430,
            "class distribution": {
                "araneae": 5,
                "carabidae": 4,
                "diptera-hymenoptera": 11,
                "opiliones": 7,
                "staphylinidae": 5
            }
        },
        "LG-OSR-LS3E20-07-13_fl": {
            "total images": 597,
            "total annotations": 78,
            "no of categories": 11,
            "positive samples": 73,
            "negative samples": 524,
            "class distribution": {
                "araneae": 3,
                "carabidae": 33,
                "diptera-hymenoptera": 28,
                "myriapoda": 7,
                "staphylinidae": 7
            }
        },
        "LG-OSR-LF2F20-07-14_fl": {
            "total images": 656,
            "total annotations": 81,
            "no of categories": 11,
            "positive samples": 76,
            "negative samples": 580,
            "class distribution": {
                "carabidae": 33,
                "dermaptera": 5,
                "diptera-hymenoptera": 15,
                "isopoda": 4,
                "myriapoda": 4,
                "staphylinidae": 20
            }
        },
        "WW-OSR-LS3E20-06-22_fl": {
            "total images": 414,
            "total annotations": 23,
            "no of categories": 11,
            "positive samples": 22,
            "negative samples": 392,
            "class distribution": {
                "araneae": 1,
                "carabidae": 21,
                "diptera-hymenoptera": 1
            }
        },
        "WW-OSR-LF1G20-06-25_fl": {
            "total images": 566,
            "total annotations": 21,
            "no of categories": 11,
            "positive samples": 21,
            "negative samples": 545,
            "class distribution": {
                "araneae": 1,
                "carabidae": 10,
                "diptera-hymenoptera": 5,
                "opiliones": 1,
                "staphylinidae": 4
            }
        },
        "GH-OSR-NARS2620-06-02_fl": {
            "total images": 507,
            "total annotations": 40,
            "no of categories": 11,
            "positive samples": 39,
            "negative samples": 468,
            "class distribution": {
                "araneae": 8,
                "carabidae": 11,
                "diptera-hymenoptera": 4,
                "staphylinidae": 17
            }
        },
        "LG-OSR-HF2F20-07-06_fl": {
            "total images": 488,
            "total annotations": 216,
            "no of categories": 11,
            "positive samples": 204,
            "negative samples": 284,
            "class distribution": {
                "araneae": 22,
                "carabidae": 2,
                "dermaptera": 1,
                "diptera-hymenoptera": 172,
                "staphylinidae": 19
            }
        },
        "LG-OSR-LF1D20-06-29_fl": {
            "total images": 544,
            "total annotations": 6,
            "no of categories": 11,
            "positive samples": 6,
            "negative samples": 538,
            "class distribution": {
                "carabidae": 4,
                "dermaptera": 2
            }
        },
        "GH-OSR-NARS3020-06-11_fl": {
            "total images": 589,
            "total annotations": 101,
            "no of categories": 11,
            "positive samples": 94,
            "negative samples": 495,
            "class distribution": {
                "araneae": 2,
                "carabidae": 52,
                "diptera-hymenoptera": 2,
                "staphylinidae": 45
            }
        },
        "LG-OSR-HF2F20-07-02_fl": {
            "total images": 511,
            "total annotations": 55,
            "no of categories": 11,
            "positive samples": 54,
            "negative samples": 457,
            "class distribution": {
                "carabidae": 53,
                "myriapoda": 2
            }
        },
        "GH-OSR-LF2E20-06-01_fl": {
            "total images": 500,
            "total annotations": 68,
            "no of categories": 11,
            "positive samples": 67,
            "negative samples": 433,
            "class distribution": {
                "araneae": 1,
                "carabidae": 2,
                "diptera-hymenoptera": 45,
                "staphylinidae": 20
            }
        },
        "LG-OSR-LF1G20-07-14_fl": {
            "total images": 518,
            "total annotations": 155,
            "no of categories": 11,
            "positive samples": 145,
            "negative samples": 373,
            "class distribution": {
                "araneae": 9,
                "carabidae": 14,
                "dermaptera": 2,
                "diptera-hymenoptera": 1,
                "myriapoda": 7,
                "staphylinidae": 122
            }
        },
        "GH-OSR-HF2G20-06-02": {
            "total images": 950,
            "total annotations": 57,
            "no of categories": 11,
            "positive samples": 54,
            "negative samples": 896,
            "class distribution": {
                "carabidae": 3,
                "diptera-hymenoptera": 46,
                "isopoda": 2,
                "staphylinidae": 6
            }
        },
        "LG-OSR-LF1G20-06-29_fl": {
            "total images": 530,
            "total annotations": 52,
            "no of categories": 11,
            "positive samples": 51,
            "negative samples": 479,
            "class distribution": {
                "araneae": 2,
                "carabidae": 37,
                "diptera-hymenoptera": 11,
                "myriapoda": 2
            }
        },
        "WW-OSR-LF2F20-06-24_fl": {
            "total images": 443,
            "total annotations": 69,
            "no of categories": 11,
            "positive samples": 67,
            "negative samples": 376,
            "class distribution": {
                "araneae": 16,
                "carabidae": 9,
                "diptera-hymenoptera": 39,
                "isopoda": 4,
                "myriapoda": 1
            }
        },
        "LG-OSR-LS3E20-07-09": {
            "total images": 118,
            "total annotations": 7,
            "no of categories": 11,
            "positive samples": 7,
            "negative samples": 111,
            "class distribution": {
                "carabidae": 7
            }
        },
        "WW-OSR-LF1D20-06-25_fl": {
            "total images": 554,
            "total annotations": 32,
            "no of categories": 11,
            "positive samples": 30,
            "negative samples": 524,
            "class distribution": {
                "araneae": 15,
                "carabidae": 14,
                "diptera-hymenoptera": 2,
                "staphylinidae": 1
            }
        },
        "GH-OSR-HF2G20-06-02_fl": {
            "total images": 556,
            "total annotations": 86,
            "no of categories": 11,
            "positive samples": 79,
            "negative samples": 477,
            "class distribution": {
                "araneae": 1,
                "carabidae": 57,
                "diptera-hymenoptera": 1,
                "isopoda": 4,
                "myriapoda": 16,
                "opiliones": 1,
                "staphylinidae": 6
            }
        },
        "WW-OSR-LS3E20-06-23_fl": {
            "total images": 447,
            "total annotations": 41,
            "no of categories": 11,
            "positive samples": 37,
            "negative samples": 410,
            "class distribution": {
                "araneae": 1,
                "carabidae": 39,
                "staphylinidae": 1
            }
        },
        "LG-OSR-LF1D20-07-14_fl": {
            "total images": 497,
            "total annotations": 42,
            "no of categories": 11,
            "positive samples": 40,
            "negative samples": 457,
            "class distribution": {
                "araneae": 2,
                "carabidae": 12,
                "diptera-hymenoptera": 1,
                "isopoda": 4,
                "myriapoda": 3,
                "staphylinidae": 20
            }
        },
        "LG-OSR-LF1G20-07-09": {
            "total images": 792,
            "total annotations": 46,
            "no of categories": 11,
            "positive samples": 46,
            "negative samples": 746,
            "class distribution": {
                "carabidae": 29,
                "coccinellidae": 2,
                "diptera-hymenoptera": 13,
                "myriapoda": 1,
                "staphylinidae": 1
            }
        },
        "GH-OSR-LF2E20-06-01": {
            "total images": 923,
            "total annotations": 33,
            "no of categories": 11,
            "positive samples": 32,
            "negative samples": 891,
            "class distribution": {
                "coleoptera (larvae)": 12,
                "diptera-hymenoptera": 19,
                "staphylinidae": 2
            }
        },
        "LG-OSR-LF2F20-06-29_fl": {
            "total images": 496,
            "total annotations": 180,
            "no of categories": 11,
            "positive samples": 167,
            "negative samples": 329,
            "class distribution": {
                "carabidae": 11,
                "dermaptera": 1,
                "diptera-hymenoptera": 162,
                "staphylinidae": 6
            }
        },
        "WW-OSR-HF2F20-06-15_fl": {
            "total images": 488,
            "total annotations": 96,
            "no of categories": 11,
            "positive samples": 89,
            "negative samples": 399,
            "class distribution": {
                "araneae": 2,
                "carabidae": 14,
                "coccinellidae": 2,
                "diptera-hymenoptera": 77,
                "staphylinidae": 1
            }
        },
        "LG-WWH-NARS3020-06-30": {
            "total images": 827,
            "total annotations": 202,
            "no of categories": 11,
            "positive samples": 186,
            "negative samples": 641,
            "class distribution": {
                "araneae": 1,
                "diptera-hymenoptera": 191,
                "isopoda": 1,
                "myriapoda": 9
            }
        },
        "WW-OSR-LF1G20-06-24_fl": {
            "total images": 506,
            "total annotations": 17,
            "no of categories": 11,
            "positive samples": 15,
            "negative samples": 491,
            "class distribution": {
                "araneae": 7,
                "carabidae": 4,
                "opiliones": 2,
                "staphylinidae": 4
            }
        },
        "GH-OSR-NARS2620-06-03_fl": {
            "total images": 546,
            "total annotations": 60,
            "no of categories": 11,
            "positive samples": 58,
            "negative samples": 488,
            "class distribution": {
                "carabidae": 6,
                "diptera-hymenoptera": 15,
                "myriapoda": 3,
                "staphylinidae": 36
            }
        },
        "LG-OSR-LF1D20-07-09": {
            "total images": 720,
            "total annotations": 13,
            "no of categories": 11,
            "positive samples": 13,
            "negative samples": 707,
            "class distribution": {
                "carabidae": 1,
                "diptera-hymenoptera": 11,
                "staphylinidae": 1
            }
        },
        "LG-OSR-LF2F20-07-06": {
            "total images": 973,
            "total annotations": 132,
            "no of categories": 11,
            "positive samples": 125,
            "negative samples": 848,
            "class distribution": {
                "carabidae": 1,
                "diptera-hymenoptera": 131
            }
        },
        "LG-OSR-LF1G20-07-15_fl": {
            "total images": 589,
            "total annotations": 88,
            "no of categories": 11,
            "positive samples": 85,
            "negative samples": 504,
            "class distribution": {
                "araneae": 2,
                "carabidae": 24,
                "dermaptera": 1,
                "diptera-hymenoptera": 1,
                "isopoda": 1,
                "myriapoda": 4,
                "staphylinidae": 55
            }
        },
        "LG-OSR-LF2F20-06-30_fl": {
            "total images": 498,
            "total annotations": 69,
            "no of categories": 11,
            "positive samples": 67,
            "negative samples": 431,
            "class distribution": {
                "araneae": 3,
                "carabidae": 51,
                "dermaptera": 4,
                "diptera-hymenoptera": 3,
                "isopoda": 1,
                "myriapoda": 2,
                "staphylinidae": 5
            }
        },
        "GH-OSR-NARS3020-06-01_fl": {
            "total images": 508,
            "total annotations": 40,
            "no of categories": 11,
            "positive samples": 39,
            "negative samples": 469,
            "class distribution": {
                "araneae": 2,
                "carabidae": 14,
                "diptera-hymenoptera": 3,
                "staphylinidae": 21
            }
        },
        "GH-OSR-NARS3020-06-01": {
            "total images": 906,
            "total annotations": 100,
            "no of categories": 11,
            "positive samples": 96,
            "negative samples": 810,
            "class distribution": {
                "cantharidae": 1,
                "carabidae": 1,
                "coleoptera (larvae)": 78,
                "diptera-hymenoptera": 15,
                "staphylinidae": 5
            }
        },
        "GH-OSR-LF2E20-06-11_fl": {
            "total images": 556,
            "total annotations": 47,
            "no of categories": 11,
            "positive samples": 45,
            "negative samples": 511,
            "class distribution": {
                "araneae": 4,
                "carabidae": 13,
                "staphylinidae": 30
            }
        },
        "LG-OSR-LF1G20-07-08_fl": {
            "total images": 587,
            "total annotations": 70,
            "no of categories": 11,
            "positive samples": 68,
            "negative samples": 519,
            "class distribution": {
                "araneae": 1,
                "carabidae": 47,
                "diptera-hymenoptera": 6,
                "myriapoda": 2,
                "staphylinidae": 14
            }
        },
        "WW-OSR-HF2F20-06-23_fl": {
            "total images": 464,
            "total annotations": 16,
            "no of categories": 11,
            "positive samples": 15,
            "negative samples": 449,
            "class distribution": {
                "araneae": 4,
                "carabidae": 7,
                "diptera-hymenoptera": 4,
                "staphylinidae": 1
            }
        },
        "GH-OSR-LF1F20-06-01_fl": {
            "total images": 479,
            "total annotations": 56,
            "no of categories": 11,
            "positive samples": 54,
            "negative samples": 425,
            "class distribution": {
                "araneae": 5,
                "carabidae": 14,
                "myriapoda": 2,
                "staphylinidae": 35
            }
        },
        "LG-OSR-LF1G20-06-30_fl": {
            "total images": 515,
            "total annotations": 91,
            "no of categories": 11,
            "positive samples": 86,
            "negative samples": 429,
            "class distribution": {
                "araneae": 2,
                "carabidae": 52,
                "diptera-hymenoptera": 9,
                "myriapoda": 11,
                "staphylinidae": 17
            }
        },
        "LG-OSR-HF2F20-07-09": {
            "total images": 786,
            "total annotations": 24,
            "no of categories": 11,
            "positive samples": 23,
            "negative samples": 763,
            "class distribution": {
                "carabidae": 11,
                "coleoptera (larvae)": 3,
                "diptera-hymenoptera": 9,
                "staphylinidae": 1
            }
        },
        "GH-OSR-NARS2620-06-03": {
            "total images": 792,
            "total annotations": 387,
            "no of categories": 11,
            "positive samples": 368,
            "negative samples": 424,
            "class distribution": {
                "araneae": 1,
                "carabidae": 3,
                "coleoptera (larvae)": 6,
                "diptera-hymenoptera": 375,
                "staphylinidae": 2
            }
        },
        "GH-OSR-LF1F20-06-02": {
            "total images": 997,
            "total annotations": 52,
            "no of categories": 11,
            "positive samples": 49,
            "negative samples": 948,
            "class distribution": {
                "coleoptera (larvae)": 9,
                "diptera-hymenoptera": 39,
                "myriapoda": 1,
                "staphylinidae": 3
            }
        },
        "LG-OSR-LF1D20-07-01_fl": {
            "total images": 557,
            "total annotations": 18,
            "no of categories": 11,
            "positive samples": 18,
            "negative samples": 539,
            "class distribution": {
                "araneae": 1,
                "carabidae": 7,
                "isopoda": 2,
                "myriapoda": 2,
                "staphylinidae": 6
            }
        },
        "LG-OSR-LF2F20-07-08_fl": {
            "total images": 555,
            "total annotations": 27,
            "no of categories": 11,
            "positive samples": 26,
            "negative samples": 529,
            "class distribution": {
                "carabidae": 22,
                "dermaptera": 1,
                "isopoda": 3,
                "staphylinidae": 1
            }
        },
        "LG-OSR-LF1D20-07-09_fl": {
            "total images": 600,
            "total annotations": 77,
            "no of categories": 11,
            "positive samples": 73,
            "negative samples": 527,
            "class distribution": {
                "araneae": 2,
                "carabidae": 25,
                "diptera-hymenoptera": 40,
                "staphylinidae": 10
            }
        },
        "WW-OSR-LS3E20-06-25_fl": {
            "total images": 498,
            "total annotations": 62,
            "no of categories": 11,
            "positive samples": 59,
            "negative samples": 439,
            "class distribution": {
                "carabidae": 54,
                "staphylinidae": 8
            }
        },
        "GH-OSR-HF2G20-06-08_fl": {
            "total images": 481,
            "total annotations": 83,
            "no of categories": 11,
            "positive samples": 79,
            "negative samples": 402,
            "class distribution": {
                "araneae": 8,
                "carabidae": 31,
                "isopoda": 1,
                "myriapoda": 30,
                "staphylinidae": 13
            }
        },
        "LG-OSR-LF2F20-07-13_fl": {
            "total images": 561,
            "total annotations": 170,
            "no of categories": 11,
            "positive samples": 135,
            "negative samples": 426,
            "class distribution": {
                "araneae": 5,
                "carabidae": 32,
                "dermaptera": 1,
                "diptera-hymenoptera": 126,
                "myriapoda": 2,
                "staphylinidae": 4
            }
        },
        "WW-OSR-LF1D20-06-23_fl": {
            "total images": 393,
            "total annotations": 24,
            "no of categories": 11,
            "positive samples": 23,
            "negative samples": 370,
            "class distribution": {
                "araneae": 4,
                "carabidae": 3,
                "diptera-hymenoptera": 17
            }
        },
        "WW-OSR-LF2F20-06-22_fl": {
            "total images": 357,
            "total annotations": 50,
            "no of categories": 11,
            "positive samples": 47,
            "negative samples": 310,
            "class distribution": {
                "araneae": 5,
                "carabidae": 16,
                "diptera-hymenoptera": 20,
                "isopoda": 2,
                "myriapoda": 5,
                "staphylinidae": 2
            }
        },
        "GH-OSR-LF2E20-06-03": {
            "total images": 807,
            "total annotations": 171,
            "no of categories": 11,
            "positive samples": 154,
            "negative samples": 653,
            "class distribution": {
                "araneae": 8,
                "carabidae": 1,
                "coleoptera (larvae)": 26,
                "diptera-hymenoptera": 120,
                "staphylinidae": 16
            }
        },
        "LG-OSR-LF1G20-07-13_fl": {
            "total images": 578,
            "total annotations": 98,
            "no of categories": 11,
            "positive samples": 88,
            "negative samples": 490,
            "class distribution": {
                "araneae": 29,
                "carabidae": 15,
                "diptera-hymenoptera": 30,
                "myriapoda": 6,
                "staphylinidae": 18
            }
        },
        "GH-OSR-LF2E20-06-02_fl": {
            "total images": 528,
            "total annotations": 90,
            "no of categories": 11,
            "positive samples": 80,
            "negative samples": 448,
            "class distribution": {
                "araneae": 2,
                "carabidae": 15,
                "diptera-hymenoptera": 54,
                "staphylinidae": 19
            }
        },
        "LG-OSR-HF2F20-07-01_fl": {
            "total images": 526,
            "total annotations": 398,
            "no of categories": 11,
            "positive samples": 307,
            "negative samples": 219,
            "class distribution": {
                "araneae": 3,
                "carabidae": 10,
                "diptera-hymenoptera": 371,
                "myriapoda": 5,
                "staphylinidae": 9
            }
        },
        "LG-OSR-HF2F20-07-09_fl": {
            "total images": 617,
            "total annotations": 19,
            "no of categories": 11,
            "positive samples": 19,
            "negative samples": 598,
            "class distribution": {
                "carabidae": 11,
                "diptera-hymenoptera": 3,
                "myriapoda": 1,
                "staphylinidae": 4
            }
        },
        "WW-OSR-LF1G20-06-22_fl": {
            "total images": 498,
            "total annotations": 185,
            "no of categories": 11,
            "positive samples": 183,
            "negative samples": 315,
            "class distribution": {
                "araneae": 1,
                "carabidae": 4,
                "diptera-hymenoptera": 179,
                "myriapoda": 1
            }
        },
        "LG-OSR-LF1G20-07-06_fl": {
            "total images": 499,
            "total annotations": 39,
            "no of categories": 11,
            "positive samples": 35,
            "negative samples": 464,
            "class distribution": {
                "araneae": 3,
                "carabidae": 9,
                "myriapoda": 8,
                "staphylinidae": 19
            }
        },
        "LG-OSR-LF1G20-07-02_fl": {
            "total images": 513,
            "total annotations": 58,
            "no of categories": 11,
            "positive samples": 55,
            "negative samples": 458,
            "class distribution": {
                "araneae": 4,
                "carabidae": 46,
                "myriapoda": 6,
                "opiliones": 1,
                "staphylinidae": 1
            }
        },
        "WW-OSR-HF2F20-06-25_fl": {
            "total images": 549,
            "total annotations": 250,
            "no of categories": 11,
            "positive samples": 206,
            "negative samples": 343,
            "class distribution": {
                "araneae": 167,
                "carabidae": 18,
                "diptera-hymenoptera": 24,
                "isopoda": 1,
                "opiliones": 35,
                "staphylinidae": 5
            }
        },
        "LG-OSR-LF2F20-07-02_fl": {
            "total images": 485,
            "total annotations": 22,
            "no of categories": 11,
            "positive samples": 21,
            "negative samples": 464,
            "class distribution": {
                "araneae": 1,
                "carabidae": 16,
                "myriapoda": 5
            }
        },
        "LG-OSR-LF2F20-07-06_fl": {
            "total images": 469,
            "total annotations": 48,
            "no of categories": 11,
            "positive samples": 48,
            "negative samples": 421,
            "class distribution": {
                "araneae": 1,
                "carabidae": 10,
                "dermaptera": 26,
                "isopoda": 2,
                "myriapoda": 1,
                "staphylinidae": 8
            }
        },
        "WW-OSR-LF1D20-06-15_fl": {
            "total images": 451,
            "total annotations": 16,
            "no of categories": 11,
            "positive samples": 16,
            "negative samples": 435,
            "class distribution": {
                "araneae": 9,
                "carabidae": 5,
                "diptera-hymenoptera": 1,
                "staphylinidae": 1
            }
        },
        "GH-OSR-HF2G20-06-11_fl": {
            "total images": 514,
            "total annotations": 133,
            "no of categories": 11,
            "positive samples": 122,
            "negative samples": 392,
            "class distribution": {
                "carabidae": 32,
                "isopoda": 5,
                "myriapoda": 95,
                "staphylinidae": 1
            }
        },
        "LG-OSR-LS3E20-07-01_fl": {
            "total images": 502,
            "total annotations": 64,
            "no of categories": 11,
            "positive samples": 62,
            "negative samples": 440,
            "class distribution": {
                "araneae": 3,
                "carabidae": 28,
                "diptera-hymenoptera": 31,
                "myriapoda": 1,
                "staphylinidae": 1
            }
        },
        "WW-OSR-HF2F20-06-24_fl": {
            "total images": 465,
            "total annotations": 33,
            "no of categories": 11,
            "positive samples": 32,
            "negative samples": 433,
            "class distribution": {
                "araneae": 14,
                "carabidae": 16,
                "diptera-hymenoptera": 1,
                "isopoda": 1,
                "opiliones": 1
            }
        },
        "LG-OSR-LF2F20-07-09": {
            "total images": 802,
            "total annotations": 74,
            "no of categories": 11,
            "positive samples": 74,
            "negative samples": 728,
            "class distribution": {
                "araneae": 1,
                "diptera-hymenoptera": 72,
                "staphylinidae": 1
            }
        },
        "LG-OSR-LS3E20-06-30_fl": {
            "total images": 516,
            "total annotations": 100,
            "no of categories": 11,
            "positive samples": 93,
            "negative samples": 423,
            "class distribution": {
                "araneae": 6,
                "carabidae": 83,
                "myriapoda": 9,
                "staphylinidae": 2
            }
        },
        "WW-OSR-LF1G20-06-15_fl": {
            "total images": 516,
            "total annotations": 5,
            "no of categories": 11,
            "positive samples": 5,
            "negative samples": 511,
            "class distribution": {
                "araneae": 3,
                "carabidae": 2
            }
        },
        "GH-OSR-NARS2620-06-11_fl": {
            "total images": 575,
            "total annotations": 70,
            "no of categories": 11,
            "positive samples": 63,
            "negative samples": 512,
            "class distribution": {
                "araneae": 10,
                "carabidae": 46,
                "diptera-hymenoptera": 5,
                "myriapoda": 4,
                "staphylinidae": 5
            }
        },
        "LG-OSR-LF1D20-07-02_fl": {
            "total images": 574,
            "total annotations": 48,
            "no of categories": 11,
            "positive samples": 47,
            "negative samples": 527,
            "class distribution": {
                "carabidae": 46,
                "isopoda": 1,
                "myriapoda": 1
            }
        },
        "LG-OSR-LF1D20-07-06_fl": {
            "total images": 477,
            "total annotations": 28,
            "no of categories": 11,
            "positive samples": 28,
            "negative samples": 449,
            "class distribution": {
                "araneae": 3,
                "carabidae": 14,
                "isopoda": 2,
                "myriapoda": 2,
                "staphylinidae": 7
            }
        },
        "WW-OSR-LF2F20-06-15_fl": {
            "total images": 458,
            "total annotations": 271,
            "no of categories": 11,
            "positive samples": 209,
            "negative samples": 249,
            "class distribution": {
                "araneae": 1,
                "carabidae": 5,
                "coccinellidae": 47,
                "diptera-hymenoptera": 210,
                "staphylinidae": 8
            }
        },
        "LG-OSR-HF2F20-06-29_fl": {
            "total images": 519,
            "total annotations": 17,
            "no of categories": 11,
            "positive samples": 17,
            "negative samples": 502,
            "class distribution": {
                "carabidae": 11,
                "diptera-hymenoptera": 4,
                "myriapoda": 2
            }
        },
        "GH-OSR-LF1F20-06-01": {
            "total images": 923,
            "total annotations": 38,
            "no of categories": 11,
            "positive samples": 37,
            "negative samples": 886,
            "class distribution": {
                "coleoptera (larvae)": 6,
                "diptera-hymenoptera": 28,
                "staphylinidae": 4
            }
        },
        "LG-OSR-LS3E20-07-08_fl": {
            "total images": 568,
            "total annotations": 40,
            "no of categories": 11,
            "positive samples": 39,
            "negative samples": 529,
            "class distribution": {
                "araneae": 1,
                "carabidae": 26,
                "myriapoda": 5,
                "staphylinidae": 8
            }
        },
        "GH-OSR-LF1F20-06-02_fl": {
            "total images": 511,
            "total annotations": 66,
            "no of categories": 11,
            "positive samples": 62,
            "negative samples": 449,
            "class distribution": {
                "araneae": 5,
                "carabidae": 14,
                "diptera-hymenoptera": 13,
                "myriapoda": 2,
                "staphylinidae": 32
            }
        },
        "LG-OSR-LF1D20-07-13_fl": {
            "total images": 608,
            "total annotations": 50,
            "no of categories": 11,
            "positive samples": 49,
            "negative samples": 559,
            "class distribution": {
                "araneae": 3,
                "carabidae": 27,
                "diptera-hymenoptera": 4,
                "myriapoda": 4,
                "staphylinidae": 12
            }
        },
        "WW-OSR-LS3E20-06-24_fl": {
            "total images": 431,
            "total annotations": 76,
            "no of categories": 11,
            "positive samples": 73,
            "negative samples": 358,
            "class distribution": {
                "araneae": 41,
                "carabidae": 29,
                "diptera-hymenoptera": 4,
                "staphylinidae": 2
            }
        },
        "GH-OSR-HF2G20-06-01_fl": {
            "total images": 542,
            "total annotations": 18,
            "no of categories": 11,
            "positive samples": 18,
            "negative samples": 524,
            "class distribution": {
                "carabidae": 8,
                "myriapoda": 5,
                "staphylinidae": 5
            }
        },
        "LG-OSR-HF2F20-06-30_fl": {
            "total images": 505,
            "total annotations": 35,
            "no of categories": 11,
            "positive samples": 32,
            "negative samples": 473,
            "class distribution": {
                "araneae": 1,
                "carabidae": 25,
                "myriapoda": 5,
                "staphylinidae": 4
            }
        },
        "WW-OSR-LF1D20-06-22_fl": {
            "total images": 405,
            "total annotations": 40,
            "no of categories": 11,
            "positive samples": 40,
            "negative samples": 365,
            "class distribution": {
                "araneae": 3,
                "carabidae": 5,
                "diptera-hymenoptera": 31,
                "isopoda": 1
            }
        },
        "WW-OSR-LF2F20-06-23_fl": {
            "total images": 462,
            "total annotations": 60,
            "no of categories": 11,
            "positive samples": 56,
            "negative samples": 406,
            "class distribution": {
                "araneae": 1,
                "carabidae": 21,
                "diptera-hymenoptera": 24,
                "isopoda": 7,
                "myriapoda": 1,
                "staphylinidae": 6
            }
        },
        "GH-OSR-LF2E20-06-03_fl": {
            "total images": 536,
            "total annotations": 21,
            "no of categories": 11,
            "positive samples": 20,
            "negative samples": 516,
            "class distribution": {
                "araneae": 3,
                "carabidae": 5,
                "coleoptera (larvae)": 2,
                "diptera-hymenoptera": 1,
                "myriapoda": 1,
                "staphylinidae": 9
            }
        },
        "LG-OSR-LS3E20-06-29_fl": {
            "total images": 524,
            "total annotations": 108,
            "no of categories": 11,
            "positive samples": 95,
            "negative samples": 429,
            "class distribution": {
                "araneae": 4,
                "carabidae": 87,
                "diptera-hymenoptera": 7,
                "myriapoda": 4,
                "staphylinidae": 6
            }
        },
        "LG-OSR-LF1G20-07-16_fl": {
            "total images": 690,
            "total annotations": 615,
            "no of categories": 11,
            "positive samples": 502,
            "negative samples": 188,
            "class distribution": {
                "carabidae": 615
            }
        },
        "LG-OSR-HF2F20-07-08_fl": {
            "total images": 566,
            "total annotations": 52,
            "no of categories": 11,
            "positive samples": 50,
            "negative samples": 516,
            "class distribution": {
                "carabidae": 37,
                "dermaptera": 1,
                "diptera-hymenoptera": 1,
                "myriapoda": 3,
                "staphylinidae": 10
            }
        },
        "WW-OSR-LF1G20-06-23_fl": {
            "total images": 369,
            "total annotations": 69,
            "no of categories": 11,
            "positive samples": 69,
            "negative samples": 300,
            "class distribution": {
                "araneae": 55,
                "carabidae": 4,
                "staphylinidae": 10
            }
        }
    }
}